{
  "indexFields": [
    {
      "multivalued": false,
      "name": "service_id",
      "path": "//*[local-name()='id']/text()",
      "type": "java.lang.String",
      "primaryKey": true
    },
    {
      "multivalued": false,
      "name": "name",
      "path": "//*[local-name()='name']/text()",
      "type": "java.lang.String"
    },
    {
      "multivalued": false,
      "name": "tagline",
      "path": "//*[local-name()='tagline']/text()",
      "type": "java.lang.String"
    },
    {
      "multivalued": false,
      "name": "fullName",
      "path": "//*[local-name()='fullName']/text()",
      "type": "java.lang.String"
    },
    {
      "multivalued": false,
      "name": "options",
      "path": "//*[local-name()='options']/text()",
      "type": "java.lang.String"
    },
    {
      "multivalued": false,
      "name": "url",
      "path": "//*[local-name()='url']/text()",
      "type": "java.lang.String"
    },
    {
      "multivalued": false,
      "name": "symbol",
      "path": "//*[local-name()='symbol']/text()",
      "type": "java.lang.String"
    },
    {
      "multivalued": false,
      "name": "multimediaURL",
      "path": "//*[local-name()='multimediaURL']/text()",
      "type": "java.lang.String"
    },
    {
      "multivalued": false,
      "name": "version",
      "path": "//*[local-name()='version']/text()",
      "type": "java.lang.String"
    },
    {
      "multivalued": false,
      "name": "lastUpdate",
      "path": "//*[local-name()='lastUpdate']/text()",
      "type": "java.util.Date"
    },
    {
      "multivalued": false,
      "name": "changeLog",
      "path": "//*[local-name()='changeLog']/text()",
      "type": "java.lang.String"
    },
    {
      "multivalued": false,
      "name": "category",
      "label": "Category",
      "path": "//*[local-name()='category']/text()",
      "type": "java.lang.String"
    },
    {
      "multivalued": false,
      "name": "provider",
      "label": "Provider",
      "path": "//*[local-name()='provider']/text()",
      "type": "java.lang.String"
    },
    {
      "multivalued": false,
      "name": "lifeCyYcleStatus",
      "label": "Phase",
      "path": "//*[local-name()='lifeCyYcleStatus']/text()",
      "type": "java.lang.String"
    },
    {
      "multivalued": false,
      "name": "trl",
      "label": "TRL",
      "path": "//*[local-name()='trl']/text()",
      "type": "java.lang.String"
    },
    {
      "multivalued": false,
      "name": "subcategory",
      "path": "//*[local-name()='subcategory']/text()",
      "type": "java.lang.String"
    },
    {
      "multivalued": true,
      "name": "place",
      "path": "//*[local-name()='place']/text()",
      "type": "java.lang.String"
    },
//    {
//      "multivalued": true,
//      "name": "region",
//      "path": "//*[local-name()='region']/text()",
//      "type": "java.lang.String"
//    },
    {
      "multivalued": true,
      "name": "language",
      "path": "//*[local-name()='language']/text()",
      "type": "java.lang.String"
    },
    {
      "multivalued": true,
      "name": "tag",
      "path": "//*[local-name()='tag']/text()",
      "type": "java.lang.String"
    },
    {
      "multivalued": true,
      "name": "relatedService",
      "path": "//*[local-name()='relatedService']/text()",
      "type": "java.lang.String"
    },
    {
      "multivalued": false,
      "name": "request",
      "path": "//*[local-name()='request']/text()",
      "type": "java.lang.String"
    },
    {
      "multivalued": false,
      "name": "helpdesk",
      "path": "//*[local-name()='helpdesk']/text()",
      "type": "java.lang.String"
    },
    {
      "multivalued": false,
      "name": "userManual",
      "path": "//*[local-name()='userManual']/text()",
      "type": "java.lang.String"
    },
    {
      "multivalued": false,
      "name": "trainingInformation",
      "path": "//*[local-name()='trainingInformation']/text()",
      "type": "java.lang.String"
    },
    {
      "multivalued": false,
      "name": "feedback",
      "path": "//*[local-name()='feedback']/text()",
      "type": "java.lang.String"
    },
    {
      "multivalued": false,
      "name": "price",
      "path": "//*[local-name()='price']/text()",
      "type": "java.lang.String"
    },
    {
      "multivalued": false,
      "name": "serviceLevelAgreement",
      "path": "//*[local-name()='serviceLevelAgreement']/text()",
      "type": "java.lang.String"
    },
    {
      "multivalued": true,
      "name": "termsOfUse",
      "path": "//*[local-name()='termsOfUse']/text()",
      "type": "java.lang.String"
    }
  ],
  "indexMapperClass": "eu.openminted.registry.core.index.DefaultIndexMapper",
  "name": "service",
  "aliasGroup": "resourceTypes",
  "payloadType": "xml",
  "schemaUrl": "https://builds.openminted.eu/job/eic-registry-model/ws/target/generated-resources/schemagen/schema1.xsd"
}